{
    "version": "1.77.0",
    "homepage": "https://gitlab.com/gitlab-org/cli",
    "license": "",
    "url": "https://gitlab.com/gitlab-org/cli/-/releases/v1.77.0/downloads/glab_1.77.0_windows_amd64.zip",
    "hash": "52e213eb10ff3b0d4c6744c3ef4393cb72aabb5b6419aaa9c9a54272081fe958",
    "bin": "bin\\glab.exe",
    "checkver": {
        "url": "https://gitlab.com/gitlab-org/cli/-/tags?format=atom",
        "regex": "/tags/v([\\d.]+)<"
    },
    "autoupdate": {
        "url": "https://gitlab.com/gitlab-org/cli/-/releases/v$version/downloads/glab_$version_windows_amd64.zip"
    }
}
